{"fields":[{"metadata":{},"name":"Id","nullable":true,"type":"string"},{"metadata":{},"name":"ZREP","nullable":true,"type":"string"},{"metadata":{},"name":"DemandCode","nullable":true,"type":"string"},{"metadata":{},"name":"InOut","nullable":true,"type":"boolean"},{"metadata":{},"name":"PromoNameId","nullable":true,"type":"string"},{"metadata":{},"name":"PromoNumber","nullable":true,"type":"integer"},{"metadata":{},"name":"LocApollo","nullable":true,"type":"string"},{"metadata":{},"name":"TypeApollo","nullable":true,"type":"string"},{"metadata":{},"name":"ModelApollo","nullable":true,"type":"string"},{"metadata":{},"name":"WeekStartDate","nullable":true,"type":"timestamp"},{"metadata":{},"name":"PlanProductIncrementalCaseQty","nullable":true,"type":"double"},{"metadata":{},"name":"PlanProductBaselineCaseQty","nullable":true,"type":"double"},{"metadata":{},"name":"PlanProductIncrementalLSV","nullable":true,"type":"double"},{"metadata":{},"name":"PlanProductBaselineLSV","nullable":true,"type":"double"},{"metadata":{},"name":"PlanUplift","nullable":true,"type":"double"},{"metadata":{},"name":"DispatchesStart","nullable":true,"type":"timestamp"},{"metadata":{},"name":"DispatchesEnd","nullable":true,"type":"timestamp"},{"metadata":{},"name":"IsGrowthAcceleration","nullable":true,"type":"boolean"},{"metadata":{},"name":"Week","nullable":true,"type":"string"},{"metadata":{},"name":"Status","nullable":true,"type":"string"},{"metadata":{},"name":"#QCCount","nullable":true,"type":"integer"}],"type":"struct"}