{"fields":[{"metadata":{},"name":"Id","nullable":true,"type":"string"},{"metadata":{},"name":"Disabled","nullable":true,"type":"integer"},{"metadata":{},"name":"DeletedDate","nullable":true,"type":"timestamp"},{"metadata":{},"name":"BrandId","nullable":true,"type":"string"},{"metadata":{},"name":"BrandTechId","nullable":true,"type":"string"},{"metadata":{},"name":"PromoStatusId","nullable":true,"type":"string"},{"metadata":{},"name":"Name","nullable":true,"type":"string"},{"metadata":{},"name":"StartDate","nullable":true,"type":"timestamp"},{"metadata":{},"name":"EndDate","nullable":true,"type":"timestamp"},{"metadata":{},"name":"DispatchesStart","nullable":true,"type":"timestamp"},{"metadata":{},"name":"DispatchesEnd","nullable":true,"type":"timestamp"},{"metadata":{},"name":"ColorId","nullable":true,"type":"string"},{"metadata":{},"name":"Number","nullable":true,"type":"integer"},{"metadata":{},"name":"RejectReasonId","nullable":true,"type":"string"},{"metadata":{},"name":"EventId","nullable":true,"type":"string"},{"metadata":{},"name":"MarsMechanicId","nullable":true,"type":"string"},{"metadata":{},"name":"MarsMechanicTypeId","nullable":true,"type":"string"},{"metadata":{},"name":"PlanInstoreMechanicId","nullable":true,"type":"string"},{"metadata":{},"name":"PlanInstoreMechanicTypeId","nullable":true,"type":"string"},{"metadata":{},"name":"MarsMechanicDiscount","nullable":true,"type":"double"},{"metadata":{},"name":"OtherEventName","nullable":true,"type":"string"},{"metadata":{},"name":"EventName","nullable":true,"type":"string"},{"metadata":{},"name":"ClientHierarchy","nullable":true,"type":"string"},{"metadata":{},"name":"ProductHierarchy","nullable":true,"type":"string"},{"metadata":{},"name":"CreatorId","nullable":true,"type":"string"},{"metadata":{},"name":"MarsStartDate","nullable":true,"type":"string"},{"metadata":{},"name":"MarsEndDate","nullable":true,"type":"string"},{"metadata":{},"name":"MarsDispatchesStart","nullable":true,"type":"string"},{"metadata":{},"name":"MarsDispatchesEnd","nullable":true,"type":"string"},{"metadata":{},"name":"ClientTreeId","nullable":true,"type":"integer"},{"metadata":{},"name":"BaseClientTreeId","nullable":true,"type":"integer"},{"metadata":{},"name":"Mechanic","nullable":true,"type":"string"},{"metadata":{},"name":"MechanicIA","nullable":true,"type":"string"},{"metadata":{},"name":"BaseClientTreeIds","nullable":true,"type":"string"},{"metadata":{},"name":"LastApprovedDate","nullable":true,"type":"timestamp"},{"metadata":{},"name":"TechnologyId","nullable":true,"type":"string"},{"metadata":{},"name":"NeedRecountUplift","nullable":true,"type":"integer"},{"metadata":{},"name":"IsAutomaticallyApproved","nullable":true,"type":"integer"},{"metadata":{},"name":"IsCMManagerApproved","nullable":true,"type":"integer"},{"metadata":{},"name":"IsDemandPlanningApproved","nullable":true,"type":"integer"},{"metadata":{},"name":"IsDemandFinanceApproved","nullable":true,"type":"integer"},{"metadata":{},"name":"PlanPromoXSites","nullable":true,"type":"double"},{"metadata":{},"name":"PlanPromoCatalogue","nullable":true,"type":"double"},{"metadata":{},"name":"PlanPromoPOSMInClient","nullable":true,"type":"double"},{"metadata":{},"name":"PlanPromoCostProdXSites","nullable":true,"type":"double"},{"metadata":{},"name":"PlanPromoCostProdCatalogue","nullable":true,"type":"double"},{"metadata":{},"name":"PlanPromoCostProdPOSMInClient","nullable":true,"type":"double"},{"metadata":{},"name":"ActualPromoXSites","nullable":true,"type":"double"},{"metadata":{},"name":"ActualPromoCatalogue","nullable":true,"type":"double"},{"metadata":{},"name":"ActualPromoPOSMInClient","nullable":true,"type":"double"},{"metadata":{},"name":"ActualPromoCostProdXSites","nullable":true,"type":"double"},{"metadata":{},"name":"ActualPromoCostProdCatalogue","nullable":true,"type":"double"},{"metadata":{},"name":"ActualPromoCostProdPOSMInClient","nullable":true,"type":"double"},{"metadata":{},"name":"MechanicComment","nullable":true,"type":"string"},{"metadata":{},"name":"PlanInstoreMechanicDiscount","nullable":true,"type":"double"},{"metadata":{},"name":"CalendarPriority","nullable":true,"type":"integer"},{"metadata":{},"name":"PlanPromoTIShopper","nullable":true,"type":"double"},{"metadata":{},"name":"PlanPromoTIMarketing","nullable":true,"type":"double"},{"metadata":{},"name":"PlanPromoBranding","nullable":true,"type":"double"},{"metadata":{},"name":"PlanPromoCost","nullable":true,"type":"double"},{"metadata":{},"name":"PlanPromoBTL","nullable":true,"type":"double"},{"metadata":{},"name":"PlanPromoCostProduction","nullable":true,"type":"double"},{"metadata":{},"name":"PlanPromoUpliftPercent","nullable":true,"type":"double"},{"metadata":{},"name":"PlanPromoIncrementalLSV","nullable":true,"type":"double"},{"metadata":{},"name":"PlanPromoLSV","nullable":true,"type":"double"},{"metadata":{},"name":"PlanPromoROIPercent","nullable":true,"type":"double"},{"metadata":{},"name":"PlanPromoIncrementalNSV","nullable":true,"type":"double"},{"metadata":{},"name":"PlanPromoNetIncrementalNSV","nullable":true,"type":"double"},{"metadata":{},"name":"PlanPromoIncrementalMAC","nullable":true,"type":"double"},{"metadata":{},"name":"ActualPromoTIShopper","nullable":true,"type":"double"},{"metadata":{},"name":"ActualPromoTIMarketing","nullable":true,"type":"double"},{"metadata":{},"name":"ActualPromoBranding","nullable":true,"type":"double"},{"metadata":{},"name":"ActualPromoBTL","nullable":true,"type":"double"},{"metadata":{},"name":"ActualPromoCostProduction","nullable":true,"type":"double"},{"metadata":{},"name":"ActualPromoCost","nullable":true,"type":"double"},{"metadata":{},"name":"ActualPromoUpliftPercent","nullable":true,"type":"double"},{"metadata":{},"name":"ActualPromoIncrementalLSV","nullable":true,"type":"double"},{"metadata":{},"name":"ActualPromoLSV","nullable":true,"type":"double"},{"metadata":{},"name":"ActualPromoROIPercent","nullable":true,"type":"double"},{"metadata":{},"name":"ActualPromoIncrementalNSV","nullable":true,"type":"double"},{"metadata":{},"name":"ActualPromoNetIncrementalNSV","nullable":true,"type":"double"},{"metadata":{},"name":"ActualPromoIncrementalMAC","nullable":true,"type":"double"},{"metadata":{},"name":"ActualInStoreMechanicId","nullable":true,"type":"string"},{"metadata":{},"name":"ActualInStoreMechanicTypeId","nullable":true,"type":"string"},{"metadata":{},"name":"PromoDuration","nullable":true,"type":"integer"},{"metadata":{},"name":"DispatchDuration","nullable":true,"type":"integer"},{"metadata":{},"name":"InvoiceNumber","nullable":true,"type":"string"},{"metadata":{},"name":"PlanPromoBaselineLSV","nullable":true,"type":"double"},{"metadata":{},"name":"PlanPromoIncrementalBaseTI","nullable":true,"type":"double"},{"metadata":{},"name":"PlanPromoIncrementalCOGS","nullable":true,"type":"double"},{"metadata":{},"name":"PlanPromoTotalCost","nullable":true,"type":"double"},{"metadata":{},"name":"PlanPromoNetIncrementalLSV","nullable":true,"type":"double"},{"metadata":{},"name":"PlanPromoNetLSV","nullable":true,"type":"double"},{"metadata":{},"name":"PlanPromoNetIncrementalMAC","nullable":true,"type":"double"},{"metadata":{},"name":"PlanPromoIncrementalEarnings","nullable":true,"type":"double"},{"metadata":{},"name":"PlanPromoNetIncrementalEarnings","nullable":true,"type":"double"},{"metadata":{},"name":"PlanPromoNetROIPercent","nullable":true,"type":"double"},{"metadata":{},"name":"PlanPromoNetUpliftPercent","nullable":true,"type":"double"},{"metadata":{},"name":"ActualPromoBaselineLSV","nullable":true,"type":"double"},{"metadata":{},"name":"ActualInStoreDiscount","nullable":true,"type":"double"},{"metadata":{},"name":"ActualInStoreShelfPrice","nullable":true,"type":"double"},{"metadata":{},"name":"ActualPromoIncrementalBaseTI","nullable":true,"type":"double"},{"metadata":{},"name":"ActualPromoIncrementalCOGS","nullable":true,"type":"double"},{"metadata":{},"name":"ActualPromoTotalCost","nullable":true,"type":"double"},{"metadata":{},"name":"ActualPromoNetIncrementalLSV","nullable":true,"type":"double"},{"metadata":{},"name":"ActualPromoNetLSV","nullable":true,"type":"double"},{"metadata":{},"name":"ActualPromoNetIncrementalMAC","nullable":true,"type":"double"},{"metadata":{},"name":"ActualPromoIncrementalEarnings","nullable":true,"type":"double"},{"metadata":{},"name":"ActualPromoNetIncrementalEarnings","nullable":true,"type":"double"},{"metadata":{},"name":"ActualPromoNetROIPercent","nullable":true,"type":"double"},{"metadata":{},"name":"ActualPromoNetUpliftPercent","nullable":true,"type":"double"},{"metadata":{},"name":"Calculating","nullable":true,"type":"integer"},{"metadata":{},"name":"BlockInformation","nullable":true,"type":"string"},{"metadata":{},"name":"PlanPromoBaselineBaseTI","nullable":true,"type":"double"},{"metadata":{},"name":"PlanPromoBaseTI","nullable":true,"type":"double"},{"metadata":{},"name":"PlanPromoNetNSV","nullable":true,"type":"double"},{"metadata":{},"name":"ActualPromoBaselineBaseTI","nullable":true,"type":"double"},{"metadata":{},"name":"ActualPromoBaseTI","nullable":true,"type":"double"},{"metadata":{},"name":"ActualPromoNetNSV","nullable":true,"type":"double"},{"metadata":{},"name":"ProductSubrangesList","nullable":true,"type":"string"},{"metadata":{},"name":"ClientTreeKeyId","nullable":true,"type":"integer"},{"metadata":{},"name":"InOut","nullable":true,"type":"integer"},{"metadata":{},"name":"PlanPromoNetIncrementalBaseTI","nullable":true,"type":"double"},{"metadata":{},"name":"PlanPromoNetIncrementalCOGS","nullable":true,"type":"double"},{"metadata":{},"name":"ActualPromoNetIncrementalBaseTI","nullable":true,"type":"double"},{"metadata":{},"name":"ActualPromoNetIncrementalCOGS","nullable":true,"type":"double"},{"metadata":{},"name":"PlanPromoNetBaseTI","nullable":true,"type":"double"},{"metadata":{},"name":"PlanPromoNSV","nullable":true,"type":"double"},{"metadata":{},"name":"ActualPromoNetBaseTI","nullable":true,"type":"double"},{"metadata":{},"name":"ActualPromoNSV","nullable":true,"type":"double"},{"metadata":{},"name":"ActualPromoLSVByCompensation","nullable":true,"type":"double"},{"metadata":{},"name":"PlanInStoreShelfPrice","nullable":true,"type":"double"},{"metadata":{},"name":"PlanPromoPostPromoEffectLSVW1","nullable":true,"type":"double"},{"metadata":{},"name":"PlanPromoPostPromoEffectLSVW2","nullable":true,"type":"double"},{"metadata":{},"name":"PlanPromoPostPromoEffectLSV","nullable":true,"type":"double"},{"metadata":{},"name":"ActualPromoPostPromoEffectLSVW1","nullable":true,"type":"double"},{"metadata":{},"name":"ActualPromoPostPromoEffectLSVW2","nullable":true,"type":"double"},{"metadata":{},"name":"ActualPromoPostPromoEffectLSV","nullable":true,"type":"double"},{"metadata":{},"name":"LoadFromTLC","nullable":true,"type":"integer"},{"metadata":{},"name":"InOutProductIds","nullable":true,"type":"string"},{"metadata":{},"name":"InOutExcludeAssortmentMatrixProductsButtonPressed","nullable":true,"type":"integer"},{"metadata":{},"name":"DocumentNumber","nullable":true,"type":"string"},{"metadata":{},"name":"LastChangedDate","nullable":true,"type":"timestamp"},{"metadata":{},"name":"LastChangedDateDemand","nullable":true,"type":"timestamp"},{"metadata":{},"name":"LastChangedDateFinance","nullable":true,"type":"timestamp"},{"metadata":{},"name":"RegularExcludedProductIds","nullable":true,"type":"string"},{"metadata":{},"name":"AdditionalUserTimestamp","nullable":true,"type":"string"},{"metadata":{},"name":"IsGrowthAcceleration","nullable":true,"type":"integer"},{"metadata":{},"name":"PromoTypesId","nullable":true,"type":"string"},{"metadata":{},"name":"CreatorLogin","nullable":true,"type":"string"},{"metadata":{},"name":"PlanTIBasePercent","nullable":true,"type":"double"},{"metadata":{},"name":"PlanCOGSPercent","nullable":true,"type":"double"},{"metadata":{},"name":"ActualTIBasePercent","nullable":true,"type":"double"},{"metadata":{},"name":"ActualCOGSPercent","nullable":true,"type":"double"},{"metadata":{},"name":"SumInvoice","nullable":true,"type":"double"},{"metadata":{},"name":"IsOnInvoice","nullable":true,"type":"integer"},{"metadata":{},"name":"ActualPromoLSVSI","nullable":true,"type":"double"},{"metadata":{},"name":"ActualPromoLSVSO","nullable":true,"type":"double"},{"metadata":{},"name":"IsApolloExport","nullable":true,"type":"integer"},{"metadata":{},"name":"DeviationCoefficient","nullable":true,"type":"double"},{"metadata":{},"name":"UseActualTI","nullable":true,"type":"integer"},{"metadata":{},"name":"UseActualCOGS","nullable":true,"type":"integer"},{"metadata":{},"name":"BudgetYear","nullable":true,"type":"integer"},{"metadata":{},"name":"PlanAddTIShopperApproved","nullable":true,"type":"double"},{"metadata":{},"name":"PlanAddTIShopperCalculated","nullable":true,"type":"double"},{"metadata":{},"name":"PlanAddTIMarketingApproved","nullable":true,"type":"double"},{"metadata":{},"name":"ActualAddTIShopper","nullable":true,"type":"double"},{"metadata":{},"name":"ActualAddTIMarketing","nullable":true,"type":"double"},{"metadata":{},"name":"ProductSubrangesListRU","nullable":true,"type":"string"},{"metadata":{},"name":"ManualInputSumInvoice","nullable":true,"type":"integer"},{"metadata":{},"name":"IsSplittable","nullable":true,"type":"integer"},{"metadata":{},"name":"PlanPromoBaselineVolume","nullable":true,"type":"double"},{"metadata":{},"name":"PlanPromoPostPromoEffectVolume","nullable":true,"type":"double"},{"metadata":{},"name":"PlanPromoPostPromoEffectVolumeW1","nullable":true,"type":"double"},{"metadata":{},"name":"PlanPromoPostPromoEffectVolumeW2","nullable":true,"type":"double"},{"metadata":{},"name":"PlanPromoIncrementalVolume","nullable":true,"type":"double"},{"metadata":{},"name":"PlanPromoNetIncrementalVolume","nullable":true,"type":"double"},{"metadata":{},"name":"ActualPromoBaselineVolume","nullable":true,"type":"double"},{"metadata":{},"name":"ActualPromoPostPromoEffectVolume","nullable":true,"type":"double"},{"metadata":{},"name":"ActualPromoVolumeByCompensation","nullable":true,"type":"double"},{"metadata":{},"name":"ActualPromoVolumeSI","nullable":true,"type":"double"},{"metadata":{},"name":"ActualPromoVolume","nullable":true,"type":"double"},{"metadata":{},"name":"ActualPromoIncrementalVolume","nullable":true,"type":"double"},{"metadata":{},"name":"ActualPromoNetIncrementalVolume","nullable":true,"type":"double"},{"metadata":{},"name":"PlanPromoIncrementalCOGSTn","nullable":true,"type":"double"},{"metadata":{},"name":"PlanPromoNetIncrementalCOGSTn","nullable":true,"type":"double"},{"metadata":{},"name":"ActualPromoIncrementalCOGSTn","nullable":true,"type":"double"},{"metadata":{},"name":"ActualPromoNetIncrementalCOGSTn","nullable":true,"type":"double"},{"metadata":{},"name":"IsLSVBased","nullable":true,"type":"integer"},{"metadata":{},"name":"PlanPromoIncrementalMACLSV","nullable":true,"type":"double"},{"metadata":{},"name":"PlanPromoNetIncrementalMACLSV","nullable":true,"type":"double"},{"metadata":{},"name":"ActualPromoIncrementalMACLSV","nullable":true,"type":"double"},{"metadata":{},"name":"ActualPromoNetIncrementalMACLSV","nullable":true,"type":"double"},{"metadata":{},"name":"PlanPromoIncrementalEarningsLSV","nullable":true,"type":"double"},{"metadata":{},"name":"PlanPromoNetIncrementalEarningsLSV","nullable":true,"type":"double"},{"metadata":{},"name":"ActualPromoIncrementalEarningsLSV","nullable":true,"type":"double"},{"metadata":{},"name":"ActualPromoNetIncrementalEarningsLSV","nullable":true,"type":"double"},{"metadata":{},"name":"PlanPromoROIPercentLSV","nullable":true,"type":"double"},{"metadata":{},"name":"PlanPromoNetROIPercentLSV","nullable":true,"type":"double"},{"metadata":{},"name":"ActualPromoROIPercentLSV","nullable":true,"type":"double"},{"metadata":{},"name":"ActualPromoNetROIPercentLSV","nullable":true,"type":"double"},{"metadata":{},"name":"PlanCOGSTn","nullable":true,"type":"double"},{"metadata":{},"name":"ActualCOGSTn","nullable":true,"type":"double"},{"metadata":{},"name":"MasterPromoId","nullable":true,"type":"string"},{"metadata":{},"name":"IsInExchange","nullable":true,"type":"integer"},{"metadata":{},"name":"LinkedPromoes","nullable":true,"type":"string"},{"metadata":{},"name":"IsGAManagerApproved","nullable":true,"type":"integer"},{"metadata":{},"name":"TPMmode","nullable":true,"type":"integer"},{"metadata":{},"name":"#QCCount","nullable":true,"type":"integer"}],"type":"struct"}