{
  "fields": [
    {
      "metadata": {
      },
      "name": "Id",
      "nullable": true,
      "type": "string"
    },
    {
      "metadata": {
      },
      "name": "Disabled",
      "nullable": true,
      "type": "integer"
    },
    {
      "metadata": {
      },
      "name": "DeletedDate",
      "nullable": true,
      "type": "timestamp"
    },
    {
      "metadata": {
      },
      "name": "PlanPromoUpliftPercent",
      "nullable": true,
      "type": "double"
    },
    {
      "metadata": {
      },
      "name": "PlanPromoBaselineLSV",
      "nullable": true,
      "type": "double"
    },
    {
      "metadata": {
      },
      "name": "PlanPromoIncrementalLSV",
      "nullable": true,
      "type": "double"
    },
    {
      "metadata": {
      },
      "name": "PlanPromoLSV",
      "nullable": true,
      "type": "double"
    },
    {
      "metadata": {
      },
      "name": "PlanPromoPostPromoEffectLSV",
      "nullable": true,
      "type": "double"
    },
    {
      "metadata": {
      },
      "name": "#QCCount",
      "nullable": true,
      "type": "integer"
    }
  ],
  "type": "struct"
}